my_module/__init__.py
my_module/module.py
temp_project_12876234-0.1.0.dist-info/METADATA
temp_project_12876234-0.1.0.dist-info/WHEEL
temp_project_12876234-0.1.0.dist-info/top_level.txt
temp_project_12876234-0.1.0.dist-info/RECORD
