Metadata-Version: 2.4
Name: temp_project_12876234
Version: 0.1.0
Summary: Краткое описание
Home-page: https://github.com/you/your-project
Author: Ваше Имя
Author-email: you@example.com
Classifier: Programming Language :: Python :: 3
Classifier: License :: OSI Approved :: MIT License
Classifier: Operating System :: OS Independent
Requires-Python: >=3.6
Dynamic: author
Dynamic: author-email
Dynamic: classifier
Dynamic: description-content-type
Dynamic: home-page
Dynamic: requires-python
Dynamic: summary
